LICENSE
MANIFEST.in
README.md
setup.py
dbharbor/__init__.py
dbharbor/access.py
dbharbor/bigquery.py
dbharbor/mysql.py
dbharbor/sql.py
dbharbor/sqlite.py
dbharbor/ssas.py
dbharbor/tools.py
dbharbor.egg-info/PKG-INFO
dbharbor.egg-info/SOURCES.txt
dbharbor.egg-info/dependency_links.txt
dbharbor.egg-info/requires.txt
dbharbor.egg-info/top_level.txt
dbharbor/MiscFiles/Microsoft.AnalysisServices.Tabular.DLL