Metadata-Version: 2.1
Name: dbharbor
Version: 0.1.8
Summary: Standardized DB Connections.
Home-page: https://github.com/edire/dbharbor.git
Author: Eric Di Re
Author-email: eric.dire@direanalytics.com
License: MIT
Requires-Python: >=3.11
License-File: LICENSE
Requires-Dist: pyodbc
Requires-Dist: sqlalchemy>=2.0
Requires-Dist: numpy
Requires-Dist: pandas>=2.1.1
Requires-Dist: pymysql
Requires-Dist: openpyxl
Requires-Dist: pythonnet
Requires-Dist: google-cloud-bigquery
Requires-Dist: pyarrow
Requires-Dist: db-dtypes
Requires-Dist: google-cloud-bigquery-storage
